{"info":{"_postman_id":"3d75dd76-724b-49a8-9e04-a9dc289e63d1","name":"Senado - Legislativo","schema":"https://schema.getpostman.com/json/collection/v2.1.0/collection.json"},"item":[{"name":"Parlamentar","item":[{"name":"Senador","item":[{"name":"atuais","id":"ce8c2379-9208-4073-a99f-c8289936b2a8","protocolProfileBehavior":{"disableBodyPruning":true,"disabledSystemHeaders":{"accept":true}},"request":{"method":"GET","header":[],"url":{"raw":"{{BASE_URL}}/dadosabertos/senador/lista/atual","host":["{{BASE_URL}}"],"path":["dadosabertos","senador","lista","atual"]}},"response":[]},{"name":"cargos","id":"0663076a-c135-4fe6-ab86-968989cc63b3","protocolProfileBehavior":{"disableBodyPruning":true,"disabledSystemHeaders":{"accept":true}},"request":{"method":"GET","header":[],"url":{"raw":"{{BASE_URL}}/dadosabertos/senador/{{SENADOR}}/cargos","host":["{{BASE_URL}}"],"path":["dadosabertos","senador","{{SENADOR}}","cargos"]}},"response":[]},{"name":"historico","id":"c4d4ef78-26f6-4e4a-bb86-23aefea85b29","protocolProfileBehavior":{"disableBodyPruning":true,"disabledSystemHeaders":{"accept":true}},"request":{"method":"GET","header":[],"url":{"raw":"{{BASE_URL}}/dadosabertos/senador/{{SENADOR}}/historico","host":["{{BASE_URL}}"],"path":["dadosabertos","senador","{{SENADOR}}","historico"]}},"response":[]},{"name":"mandatos","id":"45f2eb66-21f9-4f78-9367-78bc1dac7227","protocolProfileBehavior":{"disableBodyPruning":true,"disabledSystemHeaders":{"accept":true}},"request":{"method":"GET","header":[],"url":{"raw":"{{BASE_URL}}/dadosabertos/senador/{{SENADOR}}/mandatos","host":["{{BASE_URL}}"],"path":["dadosabertos","senador","{{SENADOR}}","mandatos"]}},"response":[]},{"name":"comissoes","id":"90742032-a9dc-4922-9ecd-ada9328d7a79","protocolProfileBehavior":{"disableBodyPruning":true,"disabledSystemHeaders":{"accept":true}},"request":{"method":"GET","header":[],"url":{"raw":"{{BASE_URL}}/dadosabertos/senador/{{SENADOR}}/comissoes","host":["{{BASE_URL}}"],"path":["dadosabertos","senador","{{SENADOR}}","comissoes"]}},"response":[]},{"name":"discursos","id":"b24a60c9-e5cd-4ca5-8325-f9255294f493","protocolProfileBehavior":{"disableBodyPruning":true,"disabledSystemHeaders":{"accept":true}},"request":{"method":"GET","header":[],"url":{"raw":"{{BASE_URL}}/dadosabertos/senador/{{SENADOR}}/discursos","host":["{{BASE_URL}}"],"path":["dadosabertos","senador","{{SENADOR}}","discursos"]}},"response":[]},{"name":"partidos","id":"3aa43afe-b79e-46cc-8007-8ac52465d3aa","protocolProfileBehavior":{"disableBodyPruning":true,"disabledSystemHeaders":{"accept":true}},"request":{"method":"GET","header":[],"url":{"raw":"{{BASE_URL}}/dadosabertos/senador/partidos","host":["{{BASE_URL}}"],"path":["dadosabertos","senador","partidos"]}},"response":[]},{"name":"afastados","id":"71c15fb0-c628-4b3d-a10a-e64c3d19db9f","protocolProfileBehavior":{"disableBodyPruning":true,"disabledSystemHeaders":{"accept":true}},"request":{"method":"GET","header":[],"url":{"raw":"{{BASE_URL}}/dadosabertos/senador/lista/afastados","host":["{{BASE_URL}}"],"path":["dadosabertos","senador","lista","afastados"]}},"response":[]},{"name":"detalhes do senador","id":"692d8fc8-f579-4aa8-921f-08dd220bd284","protocolProfileBehavior":{"disableBodyPruning":true,"disabledSystemHeaders":{"accept":true}},"request":{"method":"GET","header":[],"url":{"raw":"{{BASE_URL}}/dadosabertos/senador/{{SENADOR}}","host":["{{BASE_URL}}"],"path":["dadosabertos","senador","{{SENADOR}}"]}},"response":[]}],"id":"f15d44bc-3152-454d-8857-b2bde6de3fd3"}],"id":"6dad775f-d4bd-4322-a46a-b052927d4987"}],"event":[{"listen":"prerequest","script":{"id":"4d503be7-50d0-4054-81c7-73f98a30e123","type":"text/javascript","exec":["pm.request.headers.upsert({key : 'Accept',value : 'application/json'})"]}},{"listen":"test","script":{"id":"30eff164-9468-4d4e-985f-fa7d5abb0a98","type":"text/javascript","exec":[""]}}],"variable":[{"id":"08d52d0d-5a88-4e30-8acf-6e0b4219878b","key":"BASE_URL","value":"https://legis.senado.leg.br"},{"id":"68311e1b-a9d4-42fc-b990-52fb17c49d52","value":""}]}